fastnml/__init__.py
fastnml/reader.py
fastnml/writer.py
fastnml-2.0.3.dist-info/licenses/LICENSE.txt
fastnml-2.0.3.dist-info/METADATA
fastnml-2.0.3.dist-info/WHEEL
fastnml-2.0.3.dist-info/top_level.txt
fastnml-2.0.3.dist-info/RECORD
